.travis.yml
CHANGES.rst
CONTRIBUTORS.rst
MANIFEST.in
Makefile
README.rst
ZODB.txt
bootstrap.py
buildout.cfg
setup.py
tox.ini
docs/LICENSE.GPL
docs/LICENSE.txt
plonesocial/__init__.py
plonesocial/__init__.pyc
plonesocial.microblog.egg-info/PKG-INFO
plonesocial.microblog.egg-info/SOURCES.txt
plonesocial.microblog.egg-info/dependency_links.txt
plonesocial.microblog.egg-info/entry_points.txt
plonesocial.microblog.egg-info/namespace_packages.txt
plonesocial.microblog.egg-info/not-zip-safe
plonesocial.microblog.egg-info/requires.txt
plonesocial.microblog.egg-info/top_level.txt
plonesocial/microblog/__init__.py
plonesocial/microblog/__init__.pyc
plonesocial/microblog/configure.zcml
plonesocial/microblog/dexterity.zcml
plonesocial/microblog/interfaces.py
plonesocial/microblog/interfaces.pyc
plonesocial/microblog/migration.py
plonesocial/microblog/migration.pyc
plonesocial/microblog/permissions.zcml
plonesocial/microblog/statuscontainer.py
plonesocial/microblog/statuscontainer.pyc
plonesocial/microblog/statusupdate.py
plonesocial/microblog/statusupdate.pyc
plonesocial/microblog/synci18n.sh
plonesocial/microblog/testing.py
plonesocial/microblog/testing.pyc
plonesocial/microblog/tool.py
plonesocial/microblog/tool.pyc
plonesocial/microblog/utils.py
plonesocial/microblog/utils.pyc
plonesocial/microblog/browser/__init__.py
plonesocial/microblog/browser/__init__.pyc
plonesocial/microblog/browser/configure.zcml
plonesocial/microblog/browser/configure.zcml~
plonesocial/microblog/browser/interfaces.py
plonesocial/microblog/browser/interfaces.pyc
plonesocial/microblog/browser/interfaces.py~
plonesocial/microblog/browser/status.pt
plonesocial/microblog/browser/status.py
plonesocial/microblog/browser/status.pyc
plonesocial/microblog/browser/stylesheets/microblog.css
plonesocial/microblog/locales/manual.pot
plonesocial/microblog/locales/plone.pot
plonesocial/microblog/locales/plonesocial.microblog.pot
plonesocial/microblog/locales/en/LC_MESSAGES/plone.mo
plonesocial/microblog/locales/en/LC_MESSAGES/plone.po
plonesocial/microblog/locales/en/LC_MESSAGES/plonesocial.microblog.mo
plonesocial/microblog/locales/en/LC_MESSAGES/plonesocial.microblog.po
plonesocial/microblog/locales/es/LC_MESSAGES/plone.mo
plonesocial/microblog/locales/es/LC_MESSAGES/plone.po
plonesocial/microblog/locales/es/LC_MESSAGES/plonesocial.microblog.mo
