Metadata-Version: 1.1
Name: plonesocial.microblog
Version: 0.5.3
Summary: Simple microblogging in Plone
Home-page: http://github.com/cosent/plonesocial.microblog
Author: Guido Stevens
Author-email: guido.stevens@cosent.net
License: UNKNOWN
Keywords: plone socbiz social microblog
Platform: UNKNOWN
Classifier: Development Status :: 3 - Alpha
Classifier: Environment :: Web Environment
Classifier: Framework :: Plone :: 4.2
Classifier: Framework :: Plone :: 4.3
Classifier: Framework :: Plone
Classifier: License :: OSI Approved :: GNU General Public License v2 (GPLv2)
Classifier: Operating System :: OS Independent
Classifier: Programming Language :: Python :: 2.6
Classifier: Programming Language :: Python :: 2.7
Classifier: Programming Language :: Python
Classifier: Topic :: Software Development :: Libraries :: Python Modules
